emailsender/__init__.py
emailsender/__main__.py
emailsender/mail.py
emailsender-0.1.2.dist-info/DESCRIPTION.rst
emailsender-0.1.2.dist-info/entry_points.txt
emailsender-0.1.2.dist-info/METADATA
emailsender-0.1.2.dist-info/metadata.json
emailsender-0.1.2.dist-info/RECORD
emailsender-0.1.2.dist-info/top_level.txt
emailsender-0.1.2.dist-info/WHEEL
