Metadata-Version: 2.0
Name: emailsender
Version: 0.1.2
Summary: Cli-tool for sending emails throw specified SMTP server.
Home-page: https://github.com/dizballanze/mailsender
Author: Yuri Shikanov
Author-email: dizballanze@gmail.com
License: MIT
Platform: UNKNOWN
Classifier: License :: OSI Approved :: MIT License
Classifier: Programming Language :: Python :: 2
Classifier: Programming Language :: Python :: 2.6
Classifier: Programming Language :: Python :: 2.7
